CHANGELOG.rst
CONTRIBUTORS.rst
LICENSE.txt
MANIFEST.in
README.rst
requirements.txt
runtests.py
setup.cfg
setup.py
docs/history.rst
docs/index.rst
docs/installation.rst
docs/usage.rst
gu_django_tinymce.egg-info/PKG-INFO
gu_django_tinymce.egg-info/SOURCES.txt
gu_django_tinymce.egg-info/dependency_links.txt
gu_django_tinymce.egg-info/not-zip-safe
gu_django_tinymce.egg-info/top_level.txt
testtinymce/__init__.py
testtinymce/admin.py
testtinymce/manage.py
testtinymce/models.py
testtinymce/requirements.txt
testtinymce/settings.py
testtinymce/testtinymce.sqlite
testtinymce/urls.py
testtinymce/views.py
testtinymce/__pycache__/__init__.cpython-312.pyc
testtinymce/__pycache__/admin.cpython-312.pyc
testtinymce/__pycache__/models.cpython-312.pyc
testtinymce/__pycache__/settings.cpython-312.pyc
testtinymce/__pycache__/urls.cpython-312.pyc
testtinymce/media/uploads/custom/subdir/.e
testtinymce/media/uploads/custom/subdir/gps-700a8_psu-datasheet-ru.pdf
testtinymce/media/uploads/custom/subdir/picture14.png
testtinymce/media/uploads/custom/subdir/picture15.png
testtinymce/media/uploads/custom/subdir/picture16.png
testtinymce/migrations/0001_initial.py
testtinymce/migrations/__init__.py
testtinymce/migrations/__pycache__/0001_initial.cpython-312.pyc
testtinymce/migrations/__pycache__/__init__.cpython-312.pyc
testtinymce/templates/flatpages/default.html
tinymce/__init__.py
tinymce/compressor.py
tinymce/models.py
tinymce/settings.py
tinymce/urls.py
tinymce/views.py
tinymce/widgets.py
tinymce/__pycache__/__init__.cpython-312.pyc
tinymce/__pycache__/compressor.cpython-312.pyc
tinymce/__pycache__/models.cpython-312.pyc
tinymce/__pycache__/settings.cpython-312.pyc
tinymce/__pycache__/urls.cpython-312.pyc
tinymce/__pycache__/views.cpython-312.pyc
tinymce/__pycache__/widgets.cpython-312.pyc
tinymce/media/tiny_mce/license.txt
tinymce/media/tiny_mce/tiny_mce.js
tinymce/media/tiny_mce/tiny_mce_popup.js
tinymce/media/tiny_mce/tiny_mce_src.js
tinymce/media/tiny_mce/langs/ar.js
tinymce/media/tiny_mce/langs/az.js
tinymce/media/tiny_mce/langs/be.js
tinymce/media/tiny_mce/langs/bg.js
tinymce/media/tiny_mce/langs/bn.js
tinymce/media/tiny_mce/langs/br.js
tinymce/media/tiny_mce/langs/bs.js
