Metadata-Version: 2.1
Name: gu-django-tinymce
Version: 2.7.3
Summary: A Django application that contains a widget to render a form field as a TinyMCE editor.
Home-page: https://github.com/hu-django/tinymce
Author: Aljosa Mohorovic
Author-email: aljosa.mohorovic@gmail.com
License: MIT License
Keywords: django widget tinymce
Platform: any
Classifier: Development Status :: 5 - Production/Stable
Classifier: Environment :: Web Environment
Classifier: Framework :: Django
Classifier: Intended Audience :: Developers
Classifier: License :: OSI Approved :: MIT License
Classifier: Operating System :: OS Independent
Classifier: Programming Language :: Python
Classifier: Programming Language :: Python :: 3
Classifier: Topic :: Software Development :: Libraries :: Application Frameworks
Classifier: Topic :: Software Development :: Libraries :: Python Modules
Requires: django
Requires: gu_django_filebrowser_no_grappelli
License-File: LICENSE.txt
